jupyter_content/__init__.py
jupyter_content/__main__.py
jupyter_content/_version.py
jupyter_content/application.py
jupyter_content/application_base.py
jupyter_content/serverapplication.py
jupyter_content/content/__init__.py
jupyter_content/content/contentapp.py
jupyter_content/content/handlers.py
jupyter_content/content/gcp/__init__.py
jupyter_content/content/gcp/content.py
jupyter_content/content/gcp/test_content.py
jupyter_content/content/gcp/test_simple.py
jupyter_content/handlers/__init__.py
jupyter_content/handlers/base.py
jupyter_content/handlers/config/__init__.py
jupyter_content/handlers/config/handler.py
jupyter_content/handlers/content/__init__.py
jupyter_content/handlers/content/handler.py
jupyter_content/handlers/echo/__init__.py
jupyter_content/handlers/echo/handler.py
jupyter_content/handlers/index/__init__.py
jupyter_content/handlers/index/handler.py
jupyter_content/handlers/ping/__init__.py
jupyter_content/handlers/ping/handler.py
jupyter_content/handlers/proxy/__init__.py
jupyter_content/handlers/proxy/handler.py
jupyter_content/handlers/relay/__init__.py
jupyter_content/handlers/relay/handler.py
jupyter_content/jump/__init__.py
jupyter_content/jump/jumpapp.py
jupyter_content/static/102.jupyter-content.js
jupyter_content/static/1020.jupyter-content.js
jupyter_content/static/1050.jupyter-content.js
jupyter_content/static/1109.jupyter-content.js
jupyter_content/static/1110.jupyter-content.js
jupyter_content/static/1146.jupyter-content.js
jupyter_content/static/1292.jupyter-content.js
jupyter_content/static/1450.jupyter-content.js
jupyter_content/static/1626.jupyter-content.js
jupyter_content/static/1629.jupyter-content.js
jupyter_content/static/1696.jupyter-content.js
jupyter_content/static/1810.jupyter-content.js
jupyter_content/static/1900.jupyter-content.js
jupyter_content/static/1919.jupyter-content.js
jupyter_content/static/1935.jupyter-content.js
jupyter_content/static/1956.jupyter-content.js
jupyter_content/static/2.jupyter-content.js
jupyter_content-0.0.5.dist-info/METADATA
jupyter_content-0.0.5.dist-info/WHEEL
jupyter_content-0.0.5.dist-info/entry_points.txt
jupyter_content-0.0.5.dist-info/licenses/LICENSE
jupyter_content-0.0.5.dist-info/RECORD
